pip_services4_expressions/__init__.py
pip_services4_expressions/calculator/CalculationStack.py
pip_services4_expressions/calculator/ExpressionCalculator.py
pip_services4_expressions/calculator/ExpressionException.py
pip_services4_expressions/calculator/SyntaxErrorCode.py
pip_services4_expressions/calculator/SyntaxException.py
pip_services4_expressions/calculator/__init__.py
pip_services4_expressions/calculator/functions/DefaultFunctionCollection.py
pip_services4_expressions/calculator/functions/DelegatedFunction.py
pip_services4_expressions/calculator/functions/FunctionCollection.py
pip_services4_expressions/calculator/functions/IFunction.py
pip_services4_expressions/calculator/functions/IFunctionCollection.py
pip_services4_expressions/calculator/functions/__init__.py
pip_services4_expressions/calculator/parsers/ExpressionParser.py
pip_services4_expressions/calculator/parsers/ExpressionToken.py
pip_services4_expressions/calculator/parsers/ExpressionTokenType.py
pip_services4_expressions/calculator/parsers/__init__.py
pip_services4_expressions/calculator/tokenizers/ExpressionNumberState.py
pip_services4_expressions/calculator/tokenizers/ExpressionQuoteState.py
pip_services4_expressions/calculator/tokenizers/ExpressionSymbolState.py
pip_services4_expressions/calculator/tokenizers/ExpressionTokenizer.py
pip_services4_expressions/calculator/tokenizers/ExpressionWordState.py
pip_services4_expressions/calculator/tokenizers/__init__.py
pip_services4_expressions/calculator/variables/IVariable.py
pip_services4_expressions/calculator/variables/IVariableCollection.py
pip_services4_expressions/calculator/variables/Variable.py
pip_services4_expressions/calculator/variables/VariableCollection.py
pip_services4_expressions/calculator/variables/__init__.py
pip_services4_expressions/csv/CsvConstant.py
pip_services4_expressions/csv/CsvQuoteState.py
pip_services4_expressions/csv/CsvSymbolState.py
pip_services4_expressions/csv/CsvTokenizer.py
pip_services4_expressions-0.0.3.dist-info/LICENSE
pip_services4_expressions-0.0.3.dist-info/METADATA
pip_services4_expressions-0.0.3.dist-info/WHEEL
pip_services4_expressions-0.0.3.dist-info/top_level.txt
pip_services4_expressions-0.0.3.dist-info/zip-safe
pip_services4_expressions-0.0.3.dist-info/RECORD
