Metadata-Version: 2.1
Name: pip-services4-expressions
Version: 0.0.3
Summary: Basic portable abstractions for Pip.Services in Python
Home-page: http://github.com/pip-services4/pip-services4-python/tree/main/pip-services3-expressions-python
Author: Conceptual Vision Consulting LLC
Author-email: seroukhov@gmail.com
License: MIT
Platform: any
Classifier: Development Status :: 4 - Beta
Classifier: Intended Audience :: Developers
Classifier: License :: OSI Approved :: MIT License
Classifier: Operating System :: OS Independent
Classifier: Programming Language :: Python
Classifier: Programming Language :: Python :: 3.6
Classifier: Programming Language :: Python :: 3.7
Classifier: Programming Language :: Python :: 3.8
Classifier: Programming Language :: Python :: 3.9
Classifier: Topic :: Software Development :: Libraries :: Python Modules
License-File: LICENSE
Requires-Dist: pytest
Requires-Dist: pip-services4-commons <1.0,>=0.0.1
